{
    "1": [
        {
            "name": "qwre",
            "blocks": 1,
            "time": 5.718,
            "eaten": 0
        },
        {
            "name": "qrw",
            "blocks": 1,
            "time": 6.398,
            "eaten": 0
        },
        {
            "name": "qwr",
            "blocks": 1,
            "time": 6.955,
            "eaten": 0
        },
        {
            "name": "qwre",
            "blocks": 2,
            "time": 9.103,
            "eaten": 0
        },
        {
            "name": "leelang",
            "blocks": 2,
            "time": 9.602
        },
        {
            "name": "leelang",
            "blocks": 3,
            "time": 15.33,
            "eaten": 0
        },
        {
            "name": "NULL",
            "blocks": 2,
            "time": 17.58,
            "eaten": 0
        },
        {
            "name": "ee",
            "blocks": 7,
            "time": 22.762,
            "eaten": 1
        },
        {
            "name": "dd",
            "blocks": 4,
            "time": 27.207,
            "eaten": 1
        }
    ],
    "2": [
        {
            "name": "qre",
            "blocks": 2,
            "time": 8.32,
            "eaten": 0
        },
        {
            "name": "qwer",
            "blocks": 3,
            "time": 17.533,
            "eaten": 0
        },
        {
            "name": "qwre",
            "blocks": 3,
            "time": 19.246,
            "eaten": 0
        },
        {
            "name": "qwer",
            "blocks": 3,
            "time": 19.688,
            "eaten": 0
        },
        {
            "name": "rqwe",
            "blocks": 6,
            "time": 24.804,
            "eaten": 1
        },
        {
            "name": "NULL",
            "blocks": 3,
            "time": 46.488,
            "eaten": 0
        }
    ],
    "3": [
        {
            "name": "qwre",
            "blocks": 3,
            "time": 16.594,
            "eaten": 0
        },
        {
            "name": "qwre",
            "blocks": 3,
            "time": 21.353,
            "eaten": 0
        },
        {
            "name": "qwer",
            "blocks": 3,
            "time": 25.406,
            "eaten": 0
        },
        {
            "name": "NULL",
            "blocks": 3,
            "time": 50.575,
            "eaten": 0
        }
    ],
    "4": [
        {
            "name": "NULL",
            "blocks": 3,
            "time": 12.483,
            "eaten": 0
        },
        {
            "name": "qwer",
            "blocks": 3,
            "time": 12.928,
            "eaten": 0
        },
        {
            "name": "qwre",
            "blocks": 3,
            "time": 15.379,
            "eaten": 0
        },
        {
            "name": "qwer",
            "blocks": 3,
            "time": 21.019,
            "eaten": 0
        }
    ],
    "8": [
        {
            "name": "qwre",
            "blocks": 3,
            "time": 20.589,
            "eaten": 0
        },
        {
            "name": "NULL",
            "blocks": 3,
            "time": 35.222,
            "eaten": 0
        }
    ],
    "10": [
        {
            "name": "qwer",
            "blocks": 5,
            "time": 29.641,
            "eaten": 0
        },
        {
            "name": "NULL",
            "blocks": 5,
            "time": 37.305,
            "eaten": 0
        }
    ],
    "6": [
        {
            "name": "qwre",
            "blocks": 3,
            "time": 16.396,
            "eaten": 0
        },
        {
            "name": "qwer",
            "blocks": 1,
            "time": 17.818,
            "eaten": 0
        },
        {
            "name": "NULL",
            "blocks": 2,
            "time": 23.916,
            "eaten": 0
        }
    ],
    "9": [
        {
            "name": "qwer",
            "blocks": 3,
            "time": 11.972,
            "eaten": 0
        },
        {
            "name": "NULL",
            "blocks": 4,
            "time": 77.548,
            "eaten": 0
        }
    ],
    "7": [
        {
            "name": "qwer",
            "blocks": 4,
            "time": 18.172,
            "eaten": 0
        },
        {
            "name": "qwer",
            "blocks": 4,
            "time": 24.168,
            "eaten": 0
        },
        {
            "name": "NULL",
            "blocks": 4,
            "time": 27.893,
            "eaten": 0
        }
    ],
    "5": [
        {
            "name": "NULL",
            "blocks": 2,
            "time": 27.865,
            "eaten": 0
        }
    ]
}